bioio_czi/__init__.py
bioio_czi/bounding_box.py
bioio_czi/channels.py
bioio_czi/metadata.py
bioio_czi/pixel_sizes.py
bioio_czi/py.typed
bioio_czi/reader.py
bioio_czi/reader_metadata.py
bioio_czi/standard_metadata.py
bioio_czi/aicspylibczi_reader/__init__.py
bioio_czi/aicspylibczi_reader/reader.py
bioio_czi/aicspylibczi_reader/subblock_metadata.py
bioio_czi/czi-to-ome-xslt/.editorconfig
bioio_czi/czi-to-ome-xslt/.gitignore
bioio_czi/czi-to-ome-xslt/LICENSE
bioio_czi/czi-to-ome-xslt/README.md
bioio_czi/czi-to-ome-xslt/.github/PULL_REQUEST_TEMPLATE.md
bioio_czi/czi-to-ome-xslt/.github/ISSUE_TEMPLATE/bug_report.md
bioio_czi/czi-to-ome-xslt/.github/ISSUE_TEMPLATE/feature_request.md
bioio_czi/czi-to-ome-xslt/.github/workflows/test-main.yml
bioio_czi/czi-to-ome-xslt/.github/workflows/test-pr.yml
bioio_czi/czi-to-ome-xslt/docs/CODE_OF_CONDUCT.md
bioio_czi/czi-to-ome-xslt/docs/CONTRIBUTING.md
bioio_czi/czi-to-ome-xslt/docs/comparison/bf-converted.xml
bioio_czi/czi-to-ome-xslt/docs/comparison/xslt-converted.xml
bioio_czi/czi-to-ome-xslt/ome/ome.xsd
bioio_czi/czi-to-ome-xslt/tests/python-requirements.txt
bioio_czi/czi-to-ome-xslt/tests/test_transform.py
bioio_czi/czi-to-ome-xslt/tests/resources/031816_Paxillin_2.czi.xml
bioio_czi/czi-to-ome-xslt/tests/resources/Confocal_test_4c.czi.xml
bioio_czi/czi-to-ome-xslt/tests/resources/RBG-8bit.czi.xml
bioio_czi/czi-to-ome-xslt/tests/resources/README.md
bioio_czi/czi-to-ome-xslt/tests/resources/s_1_t_1_c_5_z_20.czi.xml
bioio_czi/czi-to-ome-xslt/tests/resources/s_1_t_1_c_5_z_20_with_subblocks.czi.xml
bioio_czi/czi-to-ome-xslt/tests/resources/s_3_t_1_c_3_z_5.czi.xml
bioio_czi/czi-to-ome-xslt/tests/resources/s_3_t_1_c_3_z_5_with_subblocks.czi.xml
bioio_czi/czi-to-ome-xslt/tests/resources/subblocks.czi.xml
bioio_czi/czi-to-ome-xslt/xslt/Channels.xsl
bioio_czi/czi-to-ome-xslt/xslt/CommonTypes.xsl
bioio_czi/czi-to-ome-xslt/xslt/Constants.xsl
bioio_czi/czi-to-ome-xslt/xslt/DocumentUser.xsl
bioio_czi/czi-to-ome-xslt/xslt/Image.xsl
bioio_czi-2.4.0.dist-info/licenses/LICENSE
bioio_czi-2.4.0.dist-info/METADATA
bioio_czi-2.4.0.dist-info/WHEEL
bioio_czi-2.4.0.dist-info/entry_points.txt
bioio_czi-2.4.0.dist-info/top_level.txt
bioio_czi-2.4.0.dist-info/RECORD
