Metadata-Version: 2.4
Name: bioio-czi
Version: 2.4.0
Summary: A Bioio reader plugin for reading czi images.
Author-email: bioio-devs <brian.whitney@alleninstitute.org>
License:                     GNU GENERAL PUBLIC LICENSE
Project-URL: Homepage, https://github.com/bioio-devs/bioio-czi
Project-URL: Bug Tracker, https://github.com/bioio-devs/bioio-czi/issues
Project-URL: Documentation, https://bioio-devs.github.io/bioio-czi
Project-URL: User Support, https://github.com/bioio-devs/bioio-czi/issues
Classifier: Development Status :: 4 - Beta
Classifier: License :: OSI Approved :: GNU General Public License v3 (GPLv3)
Classifier: Natural Language :: English
Classifier: Programming Language :: Python :: 3.10
Classifier: Programming Language :: Python :: 3.11
Classifier: Programming Language :: Python :: 3.12
Classifier: Programming Language :: Python :: 3.13
Requires-Python: >=3.10
License-File: LICENSE
Requires-Dist: aicspylibczi>=3.2.1
Requires-Dist: aiohttp
Requires-Dist: bioio-base>=3.0.0
Requires-Dist: dask[array]>=2021.4.1
Requires-Dist: fsspec>=2022.8.0
Requires-Dist: lxml>=4.6
Requires-Dist: lxml>=5; python_version >= "3.13"
Requires-Dist: ome-types>=0.3.4
Requires-Dist: pylibczirw
Requires-Dist: python-dateutil>=2.9.0.post0
Requires-Dist: requests
Requires-Dist: xarray>=2022.6.0
Provides-Extra: lint
Requires-Dist: pre-commit>=2.20.0; extra == "lint"
Provides-Extra: test
Requires-Dist: coverage>=5.1; extra == "test"
Requires-Dist: pytest>=5.4.3; extra == "test"
Requires-Dist: pytest-cov>=2.9.0; extra == "test"
Requires-Dist: pytest-raises>=0.11; extra == "test"
Dynamic: license-file
